stackit/mariadb/__init__.py
stackit/mariadb/api/__init__.py
stackit/mariadb/api/default_api.py
stackit/mariadb/api_client.py
stackit/mariadb/api_response.py
stackit/mariadb/configuration.py
stackit/mariadb/exceptions.py
stackit/mariadb/models/__init__.py
stackit/mariadb/models/backup.py
stackit/mariadb/models/create_backup_response_item.py
stackit/mariadb/models/create_instance_payload.py
stackit/mariadb/models/create_instance_response.py
stackit/mariadb/models/credentials.py
stackit/mariadb/models/credentials_list_item.py
stackit/mariadb/models/credentials_response.py
stackit/mariadb/models/error.py
stackit/mariadb/models/get_metrics_response.py
stackit/mariadb/models/instance.py
stackit/mariadb/models/instance_last_operation.py
stackit/mariadb/models/instance_parameters.py
stackit/mariadb/models/instance_schema.py
stackit/mariadb/models/list_backups_response.py
stackit/mariadb/models/list_credentials_response.py
stackit/mariadb/models/list_instances_response.py
stackit/mariadb/models/list_offerings_response.py
stackit/mariadb/models/list_restores_response.py
stackit/mariadb/models/model_schema.py
stackit/mariadb/models/offering.py
stackit/mariadb/models/partial_update_instance_payload.py
stackit/mariadb/models/plan.py
stackit/mariadb/models/raw_credentials.py
stackit/mariadb/models/restore.py
stackit/mariadb/models/trigger_restore_response.py
stackit/mariadb/models/update_backups_config_payload.py
stackit/mariadb/models/update_backups_config_response.py
stackit/mariadb/py.typed
stackit/mariadb/rest.py
stackit_mariadb-0.3.0.dist-info/LICENSE.md
stackit_mariadb-0.3.0.dist-info/METADATA
stackit_mariadb-0.3.0.dist-info/NOTICE.txt
stackit_mariadb-0.3.0.dist-info/WHEEL
stackit_mariadb-0.3.0.dist-info/RECORD
