Metadata-Version: 2.3
Name: stackit-mariadb
Version: 0.3.0
Summary: STACKIT MariaDB API
Author: STACKIT Developer Tools
Author-email: developer-tools@stackit.cloud
Requires-Python: >=3.9,<4.0
Classifier: License :: OSI Approved :: Apache Software License
Classifier: Operating System :: OS Independent
Classifier: Programming Language :: Python :: 3
Classifier: Programming Language :: Python :: 3.9
Classifier: Programming Language :: Python :: 3.10
Classifier: Programming Language :: Python :: 3.11
Classifier: Programming Language :: Python :: 3.12
Classifier: Programming Language :: Python :: 3.13
Requires-Dist: pydantic (>=2.9.2)
Requires-Dist: python-dateutil (>=2.9.0.post0)
Requires-Dist: requests (>=2.32.3)
Requires-Dist: stackit-core (>=0.0.1a)
Project-URL: Homepage, https://github.com/stackitcloud/stackit-sdk-python
Project-URL: Issues, https://github.com/stackitcloud/stackit-sdk-python/issues
